[
  {
    "name": "Marriott International",
    "website": "marriott.com",
    "hq_country": "US",
    "hq_city": "Bethesda",
    "eu_status": "non_eu",
    "industry": "Travel",
    "sub_industry": "Hotels",
    "founded_year": 1927,
    "confidence": "high"
  },
  {
    "name": "Hilton Worldwide",
    "website": "hilton.com",
    "hq_country": "US",
    "hq_city": "McLean",
    "eu_status": "non_eu",
    "industry": "Travel",
    "sub_industry": "Hotels",
    "founded_year": 1919,
    "confidence": "high"
  },
  {
    "name": "Hyatt Hotels",
    "website": "hyatt.com",
    "hq_country": "US",
    "hq_city": "Chicago",
    "eu_status": "non_eu",
    "industry": "Travel",
    "sub_industry": "Hotels",
    "founded_year": 1957,
    "confidence": "high"
  },
  {
    "name": "InterContinental Hotels Group",
    "website": "ihg.com",
    "hq_country": "GB",
    "hq_city": "Denham",
    "eu_status": "non_eu",
    "industry": "Travel",
    "sub_industry": "Hotels",
    "founded_year": 2003,
    "confidence": "high"
  },
  {
    "name": "Accor",
    "website": "accor.com",
    "hq_country": "FR",
    "hq_city": "Paris",
    "eu_status": "eu",
    "industry": "Travel",
    "sub_industry": "Hotels",
    "founded_year": 1967,
    "confidence": "high"
  },
  {
    "name": "Wyndham Hotels & Resorts",
    "website": "wyndhamhotels.com",
    "hq_country": "US",
    "hq_city": "Parsippany",
    "eu_status": "non_eu",
    "industry": "Travel",
    "sub_industry": "Hotels",
    "founded_year": 1981,
    "confidence": "high"
  },
  {
    "name": "Choice Hotels International",
    "website": "choicehotels.com",
    "hq_country": "US",
    "hq_city": "Rockville",
    "eu_status": "non_eu",
    "industry": "Travel",
    "sub_industry": "Hotels",
    "founded_year": 1939,
    "confidence": "high"
  },
  {
    "name": "Best Western Hotels",
    "website": "bestwestern.com",
    "hq_country": "US",
    "hq_city": "Phoenix",
    "eu_status": "non_eu",
    "industry": "Travel",
    "sub_industry": "Hotels",
    "founded_year": 1946,
    "confidence": "high"
  },
  {
    "name": "Radisson Hotel Group",
    "website": "radissonhotels.com",
    "hq_country": "BE",
    "hq_city": "Brussels",
    "eu_status": "eu",
    "industry": "Travel",
    "sub_industry": "Hotels",
    "founded_year": 1909,
    "confidence": "high"
  },
  {
    "name": "Four Seasons Hotels and Resorts",
    "website": "fourseasons.com",
    "hq_country": "CA",
    "hq_city": "Toronto",
    "eu_status": "non_eu",
    "industry": "Travel",
    "sub_industry": "Hotels",
    "founded_year": 1961,
    "confidence": "high"
  },
  {
    "name": "Mandarin Oriental Hotel Group",
    "website": "mandarinoriental.com",
    "hq_country": "HK",
    "hq_city": "Hong Kong",
    "eu_status": "non_eu",
    "industry": "Travel",
    "sub_industry": "Hotels",
    "founded_year": 1963,
    "confidence": "high"
  },
  {
    "name": "Shangri-La Hotels",
    "website": "shangri-la.com",
    "hq_country": "HK",
    "hq_city": "Hong Kong",
    "eu_status": "non_eu",
    "industry": "Travel",
    "sub_industry": "Hotels",
    "founded_year": 1971,
    "confidence": "high"
  },
  {
    "name": "Kempinski Hotels",
    "website": "kempinski.com",
    "hq_country": "DE",
    "hq_city": "Geneva",
    "eu_status": "eu",
    "industry": "Travel",
    "sub_industry": "Hotels",
    "founded_year": 1897,
    "confidence": "high"
  },
  {
    "name": "Meli\u00e1 Hotels International",
    "website": "melia.com",
    "hq_country": "ES",
    "hq_city": "Palma de Mallorca",
    "eu_status": "eu",
    "industry": "Travel",
    "sub_industry": "Hotels",
    "founded_year": 1956,
    "confidence": "high"
  },
  {
    "name": "NH Hotel Group",
    "website": "nh-hotels.com",
    "hq_country": "ES",
    "hq_city": "Madrid",
    "eu_status": "eu",
    "industry": "Travel",
    "sub_industry": "Hotels",
    "founded_year": 1978,
    "confidence": "high"
  },
  {
    "name": "Scandic Hotels",
    "website": "scandichotels.com",
    "hq_country": "SE",
    "hq_city": "Stockholm",
    "eu_status": "eu",
    "industry": "Travel",
    "sub_industry": "Hotels",
    "founded_year": 1963,
    "confidence": "high"
  },
  {
    "name": "Premier Inn",
    "website": "premierinn.com",
    "hq_country": "GB",
    "hq_city": "Dunstable",
    "eu_status": "non_eu",
    "industry": "Travel",
    "sub_industry": "Hotels",
    "founded_year": 1987,
    "confidence": "high"
  },
  {
    "name": "Travelodge",
    "website": "travelodge.co.uk",
    "hq_country": "GB",
    "hq_city": "Thame",
    "eu_status": "non_eu",
    "industry": "Travel",
    "sub_industry": "Hotels",
    "founded_year": 1985,
    "confidence": "high"
  },
  {
    "name": "citizenM Hotels",
    "website": "citizenm.com",
    "hq_country": "NL",
    "hq_city": "Amsterdam",
    "eu_status": "eu",
    "industry": "Travel",
    "sub_industry": "Hotels",
    "founded_year": 2008,
    "confidence": "high"
  },
  {
    "name": "Motel One",
    "website": "motel-one.com",
    "hq_country": "DE",
    "hq_city": "Munich",
    "eu_status": "eu",
    "industry": "Travel",
    "sub_industry": "Hotels",
    "founded_year": 2000,
    "confidence": "high"
  },
  {
    "name": "The Peninsula Hotels",
    "website": "peninsula.com",
    "hq_country": "HK",
    "hq_city": "Hong Kong",
    "eu_status": "non_eu",
    "industry": "Travel",
    "sub_industry": "Hotels",
    "founded_year": 1928,
    "confidence": "high"
  },
  {
    "name": "Fairmont Hotels & Resorts",
    "website": "fairmont.com",
    "hq_country": "CA",
    "hq_city": "Toronto",
    "eu_status": "non_eu",
    "industry": "Travel",
    "sub_industry": "Hotels",
    "founded_year": 1907,
    "confidence": "high"
  },
  {
    "name": "Rosewood Hotels & Resorts",
    "website": "rosewoodhotels.com",
    "hq_country": "HK",
    "hq_city": "Hong Kong",
    "eu_status": "non_eu",
    "industry": "Travel",
    "sub_industry": "Hotels",
    "founded_year": 1979,
    "confidence": "high"
  },
  {
    "name": "Aman Resorts",
    "website": "aman.com",
    "hq_country": "CH",
    "hq_city": "Zug",
    "eu_status": "non_eu",
    "industry": "Travel",
    "sub_industry": "Hotels",
    "founded_year": 1988,
    "confidence": "high"
  },
  {
    "name": "Six Senses Hotels Resorts Spas",
    "website": "sixsenses.com",
    "hq_country": "TH",
    "hq_city": "Bangkok",
    "eu_status": "non_eu",
    "industry": "Travel",
    "sub_industry": "Hotels",
    "founded_year": 1995,
    "confidence": "high"
  },
  {
    "name": "Banyan Tree Holdings",
    "website": "banyantree.com",
    "hq_country": "SG",
    "hq_city": "Singapore",
    "eu_status": "non_eu",
    "industry": "Travel",
    "sub_industry": "Hotels",
    "founded_year": 1994,
    "confidence": "high"
  },
  {
    "name": "Minor Hotels",
    "website": "minorhotels.com",
    "hq_country": "TH",
    "hq_city": "Bangkok",
    "eu_status": "non_eu",
    "industry": "Travel",
    "sub_industry": "Hotels",
    "founded_year": 1978,
    "confidence": "high"
  },
  {
    "name": "Oetker Collection",
    "website": "oetkercollection.com",
    "hq_country": "DE",
    "hq_city": "Baden-Baden",
    "eu_status": "eu",
    "industry": "Travel",
    "sub_industry": "Hotels",
    "founded_year": 1872,
    "confidence": "high"
  },
  {
    "name": "Belmond",
    "website": "belmond.com",
    "hq_country": "GB",
    "hq_city": "London",
    "eu_status": "non_eu",
    "industry": "Travel",
    "sub_industry": "Hotels",
    "founded_year": 1976,
    "confidence": "high"
  },
  {
    "name": "Dorchester Collection",
    "website": "dorchestercollection.com",
    "hq_country": "GB",
    "hq_city": "London",
    "eu_status": "non_eu",
    "industry": "Travel",
    "sub_industry": "Hotels",
    "founded_year": 1996,
    "confidence": "high"
  },
  {
    "name": "TUI Group",
    "website": "tuigroup.com",
    "hq_country": "DE",
    "hq_city": "Hanover",
    "eu_status": "eu",
    "industry": "Travel",
    "sub_industry": "Tour Operators",
    "founded_year": 1923,
    "confidence": "high"
  },
  {
    "name": "Carnival Corporation",
    "website": "carnivalcorp.com",
    "hq_country": "US",
    "hq_city": "Miami",
    "eu_status": "non_eu",
    "industry": "Travel",
    "sub_industry": "Cruise Lines",
    "founded_year": 1972,
    "confidence": "high"
  },
  {
    "name": "Royal Caribbean Group",
    "website": "royalcaribbeangroup.com",
    "hq_country": "US",
    "hq_city": "Miami",
    "eu_status": "non_eu",
    "industry": "Travel",
    "sub_industry": "Cruise Lines",
    "founded_year": 1968,
    "confidence": "high"
  },
  {
    "name": "Norwegian Cruise Line Holdings",
    "website": "nclhltd.com",
    "hq_country": "US",
    "hq_city": "Miami",
    "eu_status": "non_eu",
    "industry": "Travel",
    "sub_industry": "Cruise Lines",
    "founded_year": 1966,
    "confidence": "high"
  },
  {
    "name": "MSC Cruises",
    "website": "msccruises.com",
    "hq_country": "CH",
    "hq_city": "Geneva",
    "eu_status": "non_eu",
    "industry": "Travel",
    "sub_industry": "Cruise Lines",
    "founded_year": 1987,
    "confidence": "high"
  },
  {
    "name": "AIDA Cruises",
    "website": "aida.de",
    "hq_country": "DE",
    "hq_city": "Rostock",
    "eu_status": "eu",
    "industry": "Travel",
    "sub_industry": "Cruise Lines",
    "founded_year": 1996,
    "confidence": "high"
  },
  {
    "name": "Costa Cruises",
    "website": "costacruises.com",
    "hq_country": "IT",
    "hq_city": "Genoa",
    "eu_status": "eu",
    "industry": "Travel",
    "sub_industry": "Cruise Lines",
    "founded_year": 1854,
    "confidence": "high"
  },
  {
    "name": "Viking Cruises",
    "website": "vikingcruises.com",
    "hq_country": "CH",
    "hq_city": "Basel",
    "eu_status": "non_eu",
    "industry": "Travel",
    "sub_industry": "Cruise Lines",
    "founded_year": 1997,
    "confidence": "high"
  },
  {
    "name": "Hurtigruten",
    "website": "hurtigruten.com",
    "hq_country": "NO",
    "hq_city": "Troms\u00f8",
    "eu_status": "non_eu",
    "industry": "Travel",
    "sub_industry": "Cruise Lines",
    "founded_year": 1893,
    "confidence": "high"
  },
  {
    "name": "Ponant",
    "website": "ponant.com",
    "hq_country": "FR",
    "hq_city": "Marseille",
    "eu_status": "eu",
    "industry": "Travel",
    "sub_industry": "Cruise Lines",
    "founded_year": 1988,
    "confidence": "high"
  },
  {
    "name": "Silversea Cruises",
    "website": "silversea.com",
    "hq_country": "MC",
    "hq_city": "Monaco",
    "eu_status": "non_eu",
    "industry": "Travel",
    "sub_industry": "Cruise Lines",
    "founded_year": 1994,
    "confidence": "high"
  },
  {
    "name": "Celebrity Cruises",
    "website": "celebritycruises.com",
    "hq_country": "US",
    "hq_city": "Miami",
    "eu_status": "non_eu",
    "industry": "Travel",
    "sub_industry": "Cruise Lines",
    "founded_year": 1988,
    "confidence": "high"
  },
  {
    "name": "Princess Cruises",
    "website": "princess.com",
    "hq_country": "US",
    "hq_city": "Santa Clarita",
    "eu_status": "non_eu",
    "industry": "Travel",
    "sub_industry": "Cruise Lines",
    "founded_year": 1965,
    "confidence": "high"
  },
  {
    "name": "Holland America Line",
    "website": "hollandamerica.com",
    "hq_country": "US",
    "hq_city": "Seattle",
    "eu_status": "non_eu",
    "industry": "Travel",
    "sub_industry": "Cruise Lines",
    "founded_year": 1873,
    "confidence": "high"
  },
  {
    "name": "Cunard Line",
    "website": "cunard.com",
    "hq_country": "GB",
    "hq_city": "Southampton",
    "eu_status": "non_eu",
    "industry": "Travel",
    "sub_industry": "Cruise Lines",
    "founded_year": 1839,
    "confidence": "high"
  },
  {
    "name": "P&O Cruises",
    "website": "pocruises.com",
    "hq_country": "GB",
    "hq_city": "Southampton",
    "eu_status": "non_eu",
    "industry": "Travel",
    "sub_industry": "Cruise Lines",
    "founded_year": 1837,
    "confidence": "high"
  },
  {
    "name": "Enterprise Rent-A-Car",
    "website": "enterprise.com",
    "hq_country": "US",
    "hq_city": "St. Louis",
    "eu_status": "non_eu",
    "industry": "Travel",
    "sub_industry": "Car Rental",
    "founded_year": 1957,
    "confidence": "high"
  },
  {
    "name": "Avis Rent A Car",
    "website": "avis.com",
    "hq_country": "US",
    "hq_city": "Parsippany",
    "eu_status": "non_eu",
    "industry": "Travel",
    "sub_industry": "Car Rental",
    "founded_year": 1946,
    "confidence": "high"
  },
  {
    "name": "Europcar Mobility Group",
    "website": "europcar-group.com",
    "hq_country": "FR",
    "hq_city": "Paris",
    "eu_status": "eu",
    "industry": "Travel",
    "sub_industry": "Car Rental",
    "founded_year": 1949,
    "confidence": "high"
  },
  {
    "name": "Sixt SE",
    "website": "sixt.com",
    "hq_country": "DE",
    "hq_city": "Pullach",
    "eu_status": "eu",
    "industry": "Travel",
    "sub_industry": "Car Rental",
    "founded_year": 1912,
    "confidence": "high"
  },
  {
    "name": "Localiza",
    "website": "localiza.com",
    "hq_country": "BR",
    "hq_city": "Belo Horizonte",
    "eu_status": "non_eu",
    "industry": "Travel",
    "sub_industry": "Car Rental",
    "founded_year": 1973,
    "confidence": "high"
  },
  {
    "name": "Zipcar",
    "website": "zipcar.com",
    "hq_country": "US",
    "hq_city": "Boston",
    "eu_status": "non_eu",
    "industry": "Travel",
    "sub_industry": "Car Rental",
    "founded_year": 2000,
    "confidence": "high"
  },
  {
    "name": "Goldcar",
    "website": "goldcar.es",
    "hq_country": "ES",
    "hq_city": "Alicante",
    "eu_status": "eu",
    "industry": "Travel",
    "sub_industry": "Car Rental",
    "founded_year": 1985,
    "confidence": "high"
  },
  {
    "name": "OK Mobility",
    "website": "okmobility.com",
    "hq_country": "ES",
    "hq_city": "Palma de Mallorca",
    "eu_status": "eu",
    "industry": "Travel",
    "sub_industry": "Car Rental",
    "founded_year": 2005,
    "confidence": "high"
  },
  {
    "name": "Brussels Airlines",
    "website": "brusselsairlines.com",
    "hq_country": "BE",
    "hq_city": "Brussels",
    "eu_status": "eu",
    "industry": "Travel",
    "sub_industry": "Airlines",
    "founded_year": 2006,
    "confidence": "high"
  },
  {
    "name": "Transavia",
    "website": "transavia.com",
    "hq_country": "NL",
    "hq_city": "Schiphol",
    "eu_status": "eu",
    "industry": "Travel",
    "sub_industry": "Airlines",
    "founded_year": 1965,
    "confidence": "high"
  },
  {
    "name": "Volotea",
    "website": "volotea.com",
    "hq_country": "ES",
    "hq_city": "Barcelona",
    "eu_status": "eu",
    "industry": "Travel",
    "sub_industry": "Airlines",
    "founded_year": 2011,
    "confidence": "high"
  },
  {
    "name": "Condor Flugdienst",
    "website": "condor.com",
    "hq_country": "DE",
    "hq_city": "Frankfurt",
    "eu_status": "eu",
    "industry": "Travel",
    "sub_industry": "Airlines",
    "founded_year": 1955,
    "confidence": "high"
  },
  {
    "name": "Air Europa",
    "website": "aireuropa.com",
    "hq_country": "ES",
    "hq_city": "Palma de Mallorca",
    "eu_status": "eu",
    "industry": "Travel",
    "sub_industry": "Airlines",
    "founded_year": 1986,
    "confidence": "high"
  },
  {
    "name": "Luxair",
    "website": "luxair.lu",
    "hq_country": "LU",
    "hq_city": "Luxembourg",
    "eu_status": "eu",
    "industry": "Travel",
    "sub_industry": "Airlines",
    "founded_year": 1961,
    "confidence": "high"
  },
  {
    "name": "Croatia Airlines",
    "website": "croatiaairlines.com",
    "hq_country": "HR",
    "hq_city": "Zagreb",
    "eu_status": "eu",
    "industry": "Travel",
    "sub_industry": "Airlines",
    "founded_year": 1989,
    "confidence": "high"
  },
  {
    "name": "Czech Airlines",
    "website": "csa.cz",
    "hq_country": "CZ",
    "hq_city": "Prague",
    "eu_status": "eu",
    "industry": "Travel",
    "sub_industry": "Airlines",
    "founded_year": 1923,
    "confidence": "high"
  },
  {
    "name": "TAROM",
    "website": "tarom.ro",
    "hq_country": "RO",
    "hq_city": "Bucharest",
    "eu_status": "eu",
    "industry": "Travel",
    "sub_industry": "Airlines",
    "founded_year": 1954,
    "confidence": "high"
  },
  {
    "name": "Bulgaria Air",
    "website": "air.bg",
    "hq_country": "BG",
    "hq_city": "Sofia",
    "eu_status": "eu",
    "industry": "Travel",
    "sub_industry": "Airlines",
    "founded_year": 2002,
    "confidence": "high"
  },
  {
    "name": "Olympic Air",
    "website": "olympicair.com",
    "hq_country": "GR",
    "hq_city": "Athens",
    "eu_status": "eu",
    "industry": "Travel",
    "sub_industry": "Airlines",
    "founded_year": 2009,
    "confidence": "high"
  },
  {
    "name": "Cyprus Airways",
    "website": "cyprusairways.com",
    "hq_country": "CY",
    "hq_city": "Larnaca",
    "eu_status": "eu",
    "industry": "Travel",
    "sub_industry": "Airlines",
    "founded_year": 2016,
    "confidence": "high"
  },
  {
    "name": "Air Malta",
    "website": "airmalta.com",
    "hq_country": "MT",
    "hq_city": "Luqa",
    "eu_status": "eu",
    "industry": "Travel",
    "sub_industry": "Airlines",
    "founded_year": 1973,
    "confidence": "high"
  },
  {
    "name": "Flyr",
    "website": "flyr.com",
    "hq_country": "NO",
    "hq_city": "Fornebu",
    "eu_status": "non_eu",
    "industry": "Travel",
    "sub_industry": "Airlines",
    "founded_year": 2020,
    "confidence": "high"
  },
  {
    "name": "Air Serbia",
    "website": "airserbia.com",
    "hq_country": "RS",
    "hq_city": "Belgrade",
    "eu_status": "non_eu",
    "industry": "Travel",
    "sub_industry": "Airlines",
    "founded_year": 2013,
    "confidence": "high"
  },
  {
    "name": "AirAsia",
    "website": "airasia.com",
    "hq_country": "MY",
    "hq_city": "Kuala Lumpur",
    "eu_status": "non_eu",
    "industry": "Travel",
    "sub_industry": "Airlines",
    "founded_year": 1993,
    "confidence": "high"
  },
  {
    "name": "IndiGo",
    "website": "goindigo.in",
    "hq_country": "IN",
    "hq_city": "Gurgaon",
    "eu_status": "non_eu",
    "industry": "Travel",
    "sub_industry": "Airlines",
    "founded_year": 2006,
    "confidence": "high"
  },
  {
    "name": "VietJet Air",
    "website": "vietjetair.com",
    "hq_country": "VN",
    "hq_city": "Ho Chi Minh City",
    "eu_status": "non_eu",
    "industry": "Travel",
    "sub_industry": "Airlines",
    "founded_year": 2007,
    "confidence": "high"
  },
  {
    "name": "Cebu Pacific",
    "website": "cebupacificair.com",
    "hq_country": "PH",
    "hq_city": "Pasay",
    "eu_status": "non_eu",
    "industry": "Travel",
    "sub_industry": "Airlines",
    "founded_year": 1988,
    "confidence": "high"
  },
  {
    "name": "Lion Air",
    "website": "lionair.co.id",
    "hq_country": "ID",
    "hq_city": "Jakarta",
    "eu_status": "non_eu",
    "industry": "Travel",
    "sub_industry": "Airlines",
    "founded_year": 1999,
    "confidence": "high"
  },
  {
    "name": "Korean Air",
    "website": "koreanair.com",
    "hq_country": "KR",
    "hq_city": "Seoul",
    "eu_status": "non_eu",
    "industry": "Travel",
    "sub_industry": "Airlines",
    "founded_year": 1962,
    "confidence": "high"
  },
  {
    "name": "Asiana Airlines",
    "website": "flyasiana.com",
    "hq_country": "KR",
    "hq_city": "Seoul",
    "eu_status": "non_eu",
    "industry": "Travel",
    "sub_industry": "Airlines",
    "founded_year": 1988,
    "confidence": "high"
  },
  {
    "name": "All Nippon Airways",
    "website": "ana.co.jp",
    "hq_country": "JP",
    "hq_city": "Tokyo",
    "eu_status": "non_eu",
    "industry": "Travel",
    "sub_industry": "Airlines",
    "founded_year": 1952,
    "confidence": "high"
  },
  {
    "name": "Japan Airlines",
    "website": "jal.co.jp",
    "hq_country": "JP",
    "hq_city": "Tokyo",
    "eu_status": "non_eu",
    "industry": "Travel",
    "sub_industry": "Airlines",
    "founded_year": 1951,
    "confidence": "high"
  },
  {
    "name": "Thai Airways",
    "website": "thaiairways.com",
    "hq_country": "TH",
    "hq_city": "Bangkok",
    "eu_status": "non_eu",
    "industry": "Travel",
    "sub_industry": "Airlines",
    "founded_year": 1960,
    "confidence": "high"
  },
  {
    "name": "Garuda Indonesia",
    "website": "garuda-indonesia.com",
    "hq_country": "ID",
    "hq_city": "Jakarta",
    "eu_status": "non_eu",
    "industry": "Travel",
    "sub_industry": "Airlines",
    "founded_year": 1949,
    "confidence": "high"
  },
  {
    "name": "Malaysia Airlines",
    "website": "malaysiaairlines.com",
    "hq_country": "MY",
    "hq_city": "Kuala Lumpur",
    "eu_status": "non_eu",
    "industry": "Travel",
    "sub_industry": "Airlines",
    "founded_year": 1947,
    "confidence": "high"
  },
  {
    "name": "China Southern Airlines",
    "website": "csair.com",
    "hq_country": "CN",
    "hq_city": "Guangzhou",
    "eu_status": "non_eu",
    "industry": "Travel",
    "sub_industry": "Airlines",
    "founded_year": 1988,
    "confidence": "high"
  },
  {
    "name": "China Eastern Airlines",
    "website": "ceair.com",
    "hq_country": "CN",
    "hq_city": "Shanghai",
    "eu_status": "non_eu",
    "industry": "Travel",
    "sub_industry": "Airlines",
    "founded_year": 1988,
    "confidence": "high"
  },
  {
    "name": "Hainan Airlines",
    "website": "hainanairlines.com",
    "hq_country": "CN",
    "hq_city": "Haikou",
    "eu_status": "non_eu",
    "industry": "Travel",
    "sub_industry": "Airlines",
    "founded_year": 1993,
    "confidence": "high"
  },
  {
    "name": "Air China",
    "website": "airchina.com",
    "hq_country": "CN",
    "hq_city": "Beijing",
    "eu_status": "non_eu",
    "industry": "Travel",
    "sub_industry": "Airlines",
    "founded_year": 1988,
    "confidence": "high"
  },
  {
    "name": "Jetstar Airways",
    "website": "jetstar.com",
    "hq_country": "AU",
    "hq_city": "Melbourne",
    "eu_status": "non_eu",
    "industry": "Travel",
    "sub_industry": "Airlines",
    "founded_year": 2003,
    "confidence": "high"
  },
  {
    "name": "LATAM Airlines",
    "website": "latam.com",
    "hq_country": "CL",
    "hq_city": "Santiago",
    "eu_status": "non_eu",
    "industry": "Travel",
    "sub_industry": "Airlines",
    "founded_year": 2012,
    "confidence": "high"
  },
  {
    "name": "Avianca",
    "website": "avianca.com",
    "hq_country": "CO",
    "hq_city": "Bogot\u00e1",
    "eu_status": "non_eu",
    "industry": "Travel",
    "sub_industry": "Airlines",
    "founded_year": 1919,
    "confidence": "high"
  },
  {
    "name": "Copa Airlines",
    "website": "copaair.com",
    "hq_country": "PA",
    "hq_city": "Panama City",
    "eu_status": "non_eu",
    "industry": "Travel",
    "sub_industry": "Airlines",
    "founded_year": 1947,
    "confidence": "high"
  },
  {
    "name": "GOL Linhas A\u00e9reas",
    "website": "voegol.com.br",
    "hq_country": "BR",
    "hq_city": "S\u00e3o Paulo",
    "eu_status": "non_eu",
    "industry": "Travel",
    "sub_industry": "Airlines",
    "founded_year": 2000,
    "confidence": "high"
  },
  {
    "name": "Azul Brazilian Airlines",
    "website": "voeazul.com.br",
    "hq_country": "BR",
    "hq_city": "Barueri",
    "eu_status": "non_eu",
    "industry": "Travel",
    "sub_industry": "Airlines",
    "founded_year": 2008,
    "confidence": "high"
  },
  {
    "name": "Ethiopian Airlines",
    "website": "ethiopianairlines.com",
    "hq_country": "ET",
    "hq_city": "Addis Ababa",
    "eu_status": "non_eu",
    "industry": "Travel",
    "sub_industry": "Airlines",
    "founded_year": 1945,
    "confidence": "high"
  },
  {
    "name": "South African Airways",
    "website": "flysaa.com",
    "hq_country": "ZA",
    "hq_city": "Johannesburg",
    "eu_status": "non_eu",
    "industry": "Travel",
    "sub_industry": "Airlines",
    "founded_year": 1934,
    "confidence": "high"
  },
  {
    "name": "Kenya Airways",
    "website": "kenya-airways.com",
    "hq_country": "KE",
    "hq_city": "Nairobi",
    "eu_status": "non_eu",
    "industry": "Travel",
    "sub_industry": "Airlines",
    "founded_year": 1977,
    "confidence": "high"
  },
  {
    "name": "Royal Jordanian",
    "website": "rj.com",
    "hq_country": "JO",
    "hq_city": "Amman",
    "eu_status": "non_eu",
    "industry": "Travel",
    "sub_industry": "Airlines",
    "founded_year": 1963,
    "confidence": "high"
  },
  {
    "name": "Saudia",
    "website": "saudia.com",
    "hq_country": "SA",
    "hq_city": "Jeddah",
    "eu_status": "non_eu",
    "industry": "Travel",
    "sub_industry": "Airlines",
    "founded_year": 1945,
    "confidence": "high"
  },
  {
    "name": "Oman Air",
    "website": "omanair.com",
    "hq_country": "OM",
    "hq_city": "Muscat",
    "eu_status": "non_eu",
    "industry": "Travel",
    "sub_industry": "Airlines",
    "founded_year": 1993,
    "confidence": "high"
  },
  {
    "name": "Gulf Air",
    "website": "gulfair.com",
    "hq_country": "BH",
    "hq_city": "Muharraq",
    "eu_status": "non_eu",
    "industry": "Travel",
    "sub_industry": "Airlines",
    "founded_year": 1950,
    "confidence": "high"
  },
  {
    "name": "flydubai",
    "website": "flydubai.com",
    "hq_country": "AE",
    "hq_city": "Dubai",
    "eu_status": "non_eu",
    "industry": "Travel",
    "sub_industry": "Airlines",
    "founded_year": 2008,
    "confidence": "high"
  },
  {
    "name": "Priceline",
    "website": "priceline.com",
    "hq_country": "US",
    "hq_city": "Norwalk",
    "eu_status": "non_eu",
    "industry": "Travel",
    "sub_industry": "OTAs",
    "founded_year": 1997,
    "confidence": "high"
  },
  {
    "name": "Orbitz",
    "website": "orbitz.com",
    "hq_country": "US",
    "hq_city": "Chicago",
    "eu_status": "non_eu",
    "industry": "Travel",
    "sub_industry": "OTAs",
    "founded_year": 2001,
    "confidence": "high"
  },
  {
    "name": "Travelocity",
    "website": "travelocity.com",
    "hq_country": "US",
    "hq_city": "Dallas",
    "eu_status": "non_eu",
    "industry": "Travel",
    "sub_industry": "OTAs",
    "founded_year": 1996,
    "confidence": "high"
  },
  {
    "name": "CheapOair",
    "website": "cheapoair.com",
    "hq_country": "US",
    "hq_city": "New York",
    "eu_status": "non_eu",
    "industry": "Travel",
    "sub_industry": "OTAs",
    "founded_year": 2005,
    "confidence": "high"
  },
  {
    "name": "Trip.com Group",
    "website": "trip.com",
    "hq_country": "CN",
    "hq_city": "Shanghai",
    "eu_status": "non_eu",
    "industry": "Travel",
    "sub_industry": "OTAs",
    "founded_year": 1999,
    "confidence": "high"
  },
  {
    "name": "MakeMyTrip",
    "website": "makemytrip.com",
    "hq_country": "IN",
    "hq_city": "Gurgaon",
    "eu_status": "non_eu",
    "industry": "Travel",
    "sub_industry": "OTAs",
    "founded_year": 2000,
    "confidence": "high"
  },
  {
    "name": "Despegar",
    "website": "despegar.com",
    "hq_country": "AR",
    "hq_city": "Buenos Aires",
    "eu_status": "non_eu",
    "industry": "Travel",
    "sub_industry": "OTAs",
    "founded_year": 1999,
    "confidence": "high"
  },
  {
    "name": "Webjet",
    "website": "webjet.com.au",
    "hq_country": "AU",
    "hq_city": "Melbourne",
    "eu_status": "non_eu",
    "industry": "Travel",
    "sub_industry": "OTAs",
    "founded_year": 1998,
    "confidence": "high"
  },
  {
    "name": "Traveloka",
    "website": "traveloka.com",
    "hq_country": "ID",
    "hq_city": "Jakarta",
    "eu_status": "non_eu",
    "industry": "Travel",
    "sub_industry": "OTAs",
    "founded_year": 2012,
    "confidence": "high"
  },
  {
    "name": "Yatra",
    "website": "yatra.com",
    "hq_country": "IN",
    "hq_city": "Gurgaon",
    "eu_status": "non_eu",
    "industry": "Travel",
    "sub_industry": "OTAs",
    "founded_year": 2006,
    "confidence": "high"
  },
  {
    "name": "eDreams ODIGEO",
    "website": "edreamsodigeo.com",
    "hq_country": "ES",
    "hq_city": "Barcelona",
    "eu_status": "eu",
    "industry": "Travel",
    "sub_industry": "OTAs",
    "founded_year": 1999,
    "confidence": "high"
  },
  {
    "name": "Hotwire",
    "website": "hotwire.com",
    "hq_country": "US",
    "hq_city": "San Francisco",
    "eu_status": "non_eu",
    "industry": "Travel",
    "sub_industry": "OTAs",
    "founded_year": 2000,
    "confidence": "high"
  },
  {
    "name": "Secret Escapes",
    "website": "secretescapes.com",
    "hq_country": "GB",
    "hq_city": "London",
    "eu_status": "non_eu",
    "industry": "Travel",
    "sub_industry": "OTAs",
    "founded_year": 2010,
    "confidence": "high"
  },
  {
    "name": "On the Beach",
    "website": "onthebeach.co.uk",
    "hq_country": "GB",
    "hq_city": "Cheadle",
    "eu_status": "non_eu",
    "industry": "Travel",
    "sub_industry": "OTAs",
    "founded_year": 2004,
    "confidence": "high"
  },
  {
    "name": "Jet2holidays",
    "website": "jet2holidays.com",
    "hq_country": "GB",
    "hq_city": "Leeds",
    "eu_status": "non_eu",
    "industry": "Travel",
    "sub_industry": "Tour Operators",
    "founded_year": 2007,
    "confidence": "high"
  },
  {
    "name": "Jet2.com",
    "website": "jet2.com",
    "hq_country": "GB",
    "hq_city": "Leeds",
    "eu_status": "non_eu",
    "industry": "Travel",
    "sub_industry": "Airlines",
    "founded_year": 2002,
    "confidence": "high"
  },
  {
    "name": "Kuoni Travel",
    "website": "kuoni.com",
    "hq_country": "CH",
    "hq_city": "Zurich",
    "eu_status": "non_eu",
    "industry": "Travel",
    "sub_industry": "Tour Operators",
    "founded_year": 1906,
    "confidence": "high"
  },
  {
    "name": "Thomas Cook (New)",
    "website": "thomascook.com",
    "hq_country": "CN",
    "hq_city": "Shanghai",
    "eu_status": "non_eu",
    "industry": "Travel",
    "sub_industry": "Tour Operators",
    "founded_year": 2019,
    "confidence": "medium"
  },
  {
    "name": "DER Touristik",
    "website": "dertouristik.com",
    "hq_country": "DE",
    "hq_city": "Frankfurt",
    "eu_status": "eu",
    "industry": "Travel",
    "sub_industry": "Tour Operators",
    "founded_year": 1917,
    "confidence": "high"
  },
  {
    "name": "FTI Touristik",
    "website": "fti.de",
    "hq_country": "DE",
    "hq_city": "Munich",
    "eu_status": "eu",
    "industry": "Travel",
    "sub_industry": "Tour Operators",
    "founded_year": 1983,
    "confidence": "high"
  },
  {
    "name": "Alpitour World",
    "website": "alpitourworld.com",
    "hq_country": "IT",
    "hq_city": "Turin",
    "eu_status": "eu",
    "industry": "Travel",
    "sub_industry": "Tour Operators",
    "founded_year": 1947,
    "confidence": "high"
  },
  {
    "name": "Veratour",
    "website": "veratour.it",
    "hq_country": "IT",
    "hq_city": "Rome",
    "eu_status": "eu",
    "industry": "Travel",
    "sub_industry": "Tour Operators",
    "founded_year": 1990,
    "confidence": "high"
  },
  {
    "name": "Club Med",
    "website": "clubmed.com",
    "hq_country": "FR",
    "hq_city": "Paris",
    "eu_status": "eu",
    "industry": "Travel",
    "sub_industry": "Tour Operators",
    "founded_year": 1950,
    "confidence": "high"
  },
  {
    "name": "Pierre & Vacances",
    "website": "pierreetvacances.com",
    "hq_country": "FR",
    "hq_city": "Paris",
    "eu_status": "eu",
    "industry": "Travel",
    "sub_industry": "Tour Operators",
    "founded_year": 1967,
    "confidence": "high"
  },
  {
    "name": "Sunweb Group",
    "website": "sunwebgroup.com",
    "hq_country": "NL",
    "hq_city": "Rotterdam",
    "eu_status": "eu",
    "industry": "Travel",
    "sub_industry": "Tour Operators",
    "founded_year": 2000,
    "confidence": "high"
  },
  {
    "name": "Corendon",
    "website": "corendon.com",
    "hq_country": "NL",
    "hq_city": "Lijnden",
    "eu_status": "eu",
    "industry": "Travel",
    "sub_industry": "Tour Operators",
    "founded_year": 2000,
    "confidence": "high"
  },
  {
    "name": "Apollo Travel Group",
    "website": "apollo.se",
    "hq_country": "SE",
    "hq_city": "Stockholm",
    "eu_status": "eu",
    "industry": "Travel",
    "sub_industry": "Tour Operators",
    "founded_year": 1986,
    "confidence": "high"
  },
  {
    "name": "Ving",
    "website": "ving.se",
    "hq_country": "SE",
    "hq_city": "Stockholm",
    "eu_status": "eu",
    "industry": "Travel",
    "sub_industry": "Tour Operators",
    "founded_year": 1956,
    "confidence": "high"
  },
  {
    "name": "Aurinkomatkat",
    "website": "aurinkomatkat.fi",
    "hq_country": "FI",
    "hq_city": "Helsinki",
    "eu_status": "eu",
    "industry": "Travel",
    "sub_industry": "Tour Operators",
    "founded_year": 1963,
    "confidence": "high"
  },
  {
    "name": "TUI Nordic",
    "website": "tui.fi",
    "hq_country": "FI",
    "hq_city": "Vantaa",
    "eu_status": "eu",
    "industry": "Travel",
    "sub_industry": "Tour Operators",
    "founded_year": 1965,
    "confidence": "high"
  },
  {
    "name": "Hays Travel",
    "website": "haystravel.co.uk",
    "hq_country": "GB",
    "hq_city": "Sunderland",
    "eu_status": "non_eu",
    "industry": "Travel",
    "sub_industry": "Tour Operators",
    "founded_year": 1980,
    "confidence": "high"
  },
  {
    "name": "Intrepid Travel",
    "website": "intrepidtravel.com",
    "hq_country": "AU",
    "hq_city": "Melbourne",
    "eu_status": "non_eu",
    "industry": "Travel",
    "sub_industry": "Tour Operators",
    "founded_year": 1989,
    "confidence": "high"
  },
  {
    "name": "G Adventures",
    "website": "gadventures.com",
    "hq_country": "CA",
    "hq_city": "Toronto",
    "eu_status": "non_eu",
    "industry": "Travel",
    "sub_industry": "Tour Operators",
    "founded_year": 1990,
    "confidence": "high"
  },
  {
    "name": "Contiki",
    "website": "contiki.com",
    "hq_country": "CH",
    "hq_city": "Zurich",
    "eu_status": "non_eu",
    "industry": "Travel",
    "sub_industry": "Tour Operators",
    "founded_year": 1962,
    "confidence": "high"
  },
  {
    "name": "Trafalgar Tours",
    "website": "trafalgar.com",
    "hq_country": "CH",
    "hq_city": "Zurich",
    "eu_status": "non_eu",
    "industry": "Travel",
    "sub_industry": "Tour Operators",
    "founded_year": 1947,
    "confidence": "high"
  },
  {
    "name": "Globus Tours",
    "website": "globusjourneys.com",
    "hq_country": "CH",
    "hq_city": "Zurich",
    "eu_status": "non_eu",
    "industry": "Travel",
    "sub_industry": "Tour Operators",
    "founded_year": 1928,
    "confidence": "high"
  },
  {
    "name": "Insight Vacations",
    "website": "insightvacations.com",
    "hq_country": "CH",
    "hq_city": "Zurich",
    "eu_status": "non_eu",
    "industry": "Travel",
    "sub_industry": "Tour Operators",
    "founded_year": 1978,
    "confidence": "high"
  },
  {
    "name": "Europamundo Vacaciones",
    "website": "europamundo.com",
    "hq_country": "ES",
    "hq_city": "Madrid",
    "eu_status": "eu",
    "industry": "Travel",
    "sub_industry": "Tour Operators",
    "founded_year": 1993,
    "confidence": "high"
  },
  {
    "name": "Fraport AG",
    "website": "fraport.com",
    "hq_country": "DE",
    "hq_city": "Frankfurt",
    "eu_status": "eu",
    "industry": "Travel",
    "sub_industry": "Airports",
    "founded_year": 2001,
    "confidence": "high"
  },
  {
    "name": "A\u00e9roports de Paris",
    "website": "parisaeroport.fr",
    "hq_country": "FR",
    "hq_city": "Paris",
    "eu_status": "eu",
    "industry": "Travel",
    "sub_industry": "Airports",
    "founded_year": 1945,
    "confidence": "high"
  },
  {
    "name": "Heathrow Airport Holdings",
    "website": "heathrow.com",
    "hq_country": "GB",
    "hq_city": "London",
    "eu_status": "non_eu",
    "industry": "Travel",
    "sub_industry": "Airports",
    "founded_year": 1966,
    "confidence": "high"
  },
  {
    "name": "AENA",
    "website": "aena.es",
    "hq_country": "ES",
    "hq_city": "Madrid",
    "eu_status": "eu",
    "industry": "Travel",
    "sub_industry": "Airports",
    "founded_year": 1991,
    "confidence": "high"
  },
  {
    "name": "Schiphol Group",
    "website": "schiphol.nl",
    "hq_country": "NL",
    "hq_city": "Schiphol",
    "eu_status": "eu",
    "industry": "Travel",
    "sub_industry": "Airports",
    "founded_year": 1958,
    "confidence": "high"
  },
  {
    "name": "Flughafen Z\u00fcrich AG",
    "website": "zurich-airport.com",
    "hq_country": "CH",
    "hq_city": "Zurich",
    "eu_status": "non_eu",
    "industry": "Travel",
    "sub_industry": "Airports",
    "founded_year": 2000,
    "confidence": "high"
  },
  {
    "name": "Munich Airport",
    "website": "munich-airport.de",
    "hq_country": "DE",
    "hq_city": "Munich",
    "eu_status": "eu",
    "industry": "Travel",
    "sub_industry": "Airports",
    "founded_year": 1992,
    "confidence": "high"
  },
  {
    "name": "Vienna Airport",
    "website": "viennaairport.com",
    "hq_country": "AT",
    "hq_city": "Schwechat",
    "eu_status": "eu",
    "industry": "Travel",
    "sub_industry": "Airports",
    "founded_year": 1954,
    "confidence": "high"
  },
  {
    "name": "Copenhagen Airports",
    "website": "cph.dk",
    "hq_country": "DK",
    "hq_city": "Copenhagen",
    "eu_status": "eu",
    "industry": "Travel",
    "sub_industry": "Airports",
    "founded_year": 1925,
    "confidence": "high"
  },
  {
    "name": "Swedavia",
    "website": "swedavia.com",
    "hq_country": "SE",
    "hq_city": "Stockholm",
    "eu_status": "eu",
    "industry": "Travel",
    "sub_industry": "Airports",
    "founded_year": 2010,
    "confidence": "high"
  },
  {
    "name": "Finavia",
    "website": "finavia.fi",
    "hq_country": "FI",
    "hq_city": "Vantaa",
    "eu_status": "eu",
    "industry": "Travel",
    "sub_industry": "Airports",
    "founded_year": 2010,
    "confidence": "high"
  },
  {
    "name": "Avinor",
    "website": "avinor.no",
    "hq_country": "NO",
    "hq_city": "Oslo",
    "eu_status": "non_eu",
    "industry": "Travel",
    "sub_industry": "Airports",
    "founded_year": 2003,
    "confidence": "high"
  },
  {
    "name": "Brussels Airport Company",
    "website": "brusselsairport.be",
    "hq_country": "BE",
    "hq_city": "Zaventem",
    "eu_status": "eu",
    "industry": "Travel",
    "sub_industry": "Airports",
    "founded_year": 1958,
    "confidence": "high"
  },
  {
    "name": "SEA Aeroporti di Milano",
    "website": "milanomalpensa-airport.com",
    "hq_country": "IT",
    "hq_city": "Milan",
    "eu_status": "eu",
    "industry": "Travel",
    "sub_industry": "Airports",
    "founded_year": 1948,
    "confidence": "high"
  },
  {
    "name": "Aeroporti di Roma",
    "website": "adr.it",
    "hq_country": "IT",
    "hq_city": "Rome",
    "eu_status": "eu",
    "industry": "Travel",
    "sub_industry": "Airports",
    "founded_year": 1974,
    "confidence": "high"
  },
  {
    "name": "Dublin Airport Authority",
    "website": "daa.ie",
    "hq_country": "IE",
    "hq_city": "Dublin",
    "eu_status": "eu",
    "industry": "Travel",
    "sub_industry": "Airports",
    "founded_year": 2004,
    "confidence": "high"
  },
  {
    "name": "Manchester Airports Group",
    "website": "magairports.com",
    "hq_country": "GB",
    "hq_city": "Manchester",
    "eu_status": "non_eu",
    "industry": "Travel",
    "sub_industry": "Airports",
    "founded_year": 2001,
    "confidence": "high"
  },
  {
    "name": "Changi Airport Group",
    "website": "changiairport.com",
    "hq_country": "SG",
    "hq_city": "Singapore",
    "eu_status": "non_eu",
    "industry": "Travel",
    "sub_industry": "Airports",
    "founded_year": 2009,
    "confidence": "high"
  },
  {
    "name": "Sydney Airport Corporation",
    "website": "sydneyairport.com.au",
    "hq_country": "AU",
    "hq_city": "Sydney",
    "eu_status": "non_eu",
    "industry": "Travel",
    "sub_industry": "Airports",
    "founded_year": 2002,
    "confidence": "high"
  },
  {
    "name": "Auckland Airport",
    "website": "aucklandairport.co.nz",
    "hq_country": "NZ",
    "hq_city": "Auckland",
    "eu_status": "non_eu",
    "industry": "Travel",
    "sub_industry": "Airports",
    "founded_year": 1966,
    "confidence": "high"
  },
  {
    "name": "Dubai Airports",
    "website": "dubaiairports.ae",
    "hq_country": "AE",
    "hq_city": "Dubai",
    "eu_status": "non_eu",
    "industry": "Travel",
    "sub_industry": "Airports",
    "founded_year": 2007,
    "confidence": "high"
  },
  {
    "name": "Amadeus IT Group",
    "website": "amadeus.com",
    "hq_country": "ES",
    "hq_city": "Madrid",
    "eu_status": "eu",
    "industry": "Travel",
    "sub_industry": "Travel Technology",
    "founded_year": 1987,
    "confidence": "high"
  },
  {
    "name": "Sabre Corporation",
    "website": "sabre.com",
    "hq_country": "US",
    "hq_city": "Southlake",
    "eu_status": "non_eu",
    "industry": "Travel",
    "sub_industry": "Travel Technology",
    "founded_year": 1960,
    "confidence": "high"
  },
  {
    "name": "Travelport",
    "website": "travelport.com",
    "hq_country": "GB",
    "hq_city": "London",
    "eu_status": "non_eu",
    "industry": "Travel",
    "sub_industry": "Travel Technology",
    "founded_year": 2006,
    "confidence": "high"
  },
  {
    "name": "OAG",
    "website": "oag.com",
    "hq_country": "GB",
    "hq_city": "Luton",
    "eu_status": "non_eu",
    "industry": "Travel",
    "sub_industry": "Travel Technology",
    "founded_year": 1929,
    "confidence": "high"
  },
  {
    "name": "Sojern",
    "website": "sojern.com",
    "hq_country": "US",
    "hq_city": "San Francisco",
    "eu_status": "non_eu",
    "industry": "Travel",
    "sub_industry": "Travel Technology",
    "founded_year": 2007,
    "confidence": "high"
  },
  {
    "name": "SiteMinder",
    "website": "siteminder.com",
    "hq_country": "AU",
    "hq_city": "Sydney",
    "eu_status": "non_eu",
    "industry": "Travel",
    "sub_industry": "Travel Technology",
    "founded_year": 2006,
    "confidence": "high"
  },
  {
    "name": "RateGain",
    "website": "rategain.com",
    "hq_country": "IN",
    "hq_city": "Noida",
    "eu_status": "non_eu",
    "industry": "Travel",
    "sub_industry": "Travel Technology",
    "founded_year": 2004,
    "confidence": "high"
  },
  {
    "name": "HRS Group",
    "website": "hrs.com",
    "hq_country": "DE",
    "hq_city": "Cologne",
    "eu_status": "eu",
    "industry": "Travel",
    "sub_industry": "Travel Technology",
    "founded_year": 1972,
    "confidence": "high"
  },
  {
    "name": "Mews",
    "website": "mews.com",
    "hq_country": "CZ",
    "hq_city": "Prague",
    "eu_status": "eu",
    "industry": "Travel",
    "sub_industry": "Travel Technology",
    "founded_year": 2012,
    "confidence": "high"
  },
  {
    "name": "Cloudbeds",
    "website": "cloudbeds.com",
    "hq_country": "US",
    "hq_city": "San Diego",
    "eu_status": "non_eu",
    "industry": "Travel",
    "sub_industry": "Travel Technology",
    "founded_year": 2012,
    "confidence": "high"
  },
  {
    "name": "Sonder Holdings",
    "website": "sonder.com",
    "hq_country": "US",
    "hq_city": "San Francisco",
    "eu_status": "non_eu",
    "industry": "Travel",
    "sub_industry": "Hotels",
    "founded_year": 2014,
    "confidence": "high"
  },
  {
    "name": "Selina Hospitality",
    "website": "selina.com",
    "hq_country": "PA",
    "hq_city": "Panama City",
    "eu_status": "non_eu",
    "industry": "Travel",
    "sub_industry": "Hotels",
    "founded_year": 2015,
    "confidence": "high"
  },
  {
    "name": "OYO Rooms",
    "website": "oyorooms.com",
    "hq_country": "IN",
    "hq_city": "Gurgaon",
    "eu_status": "non_eu",
    "industry": "Travel",
    "sub_industry": "Hotels",
    "founded_year": 2013,
    "confidence": "high"
  },
  {
    "name": "Treebo Hotels",
    "website": "treebo.com",
    "hq_country": "IN",
    "hq_city": "Bangalore",
    "eu_status": "non_eu",
    "industry": "Travel",
    "sub_industry": "Hotels",
    "founded_year": 2015,
    "confidence": "high"
  },
  {
    "name": "Lemon Tree Hotels",
    "website": "lemontreehotels.com",
    "hq_country": "IN",
    "hq_city": "Gurgaon",
    "eu_status": "non_eu",
    "industry": "Travel",
    "sub_industry": "Hotels",
    "founded_year": 2002,
    "confidence": "high"
  },
  {
    "name": "Jin Jiang International",
    "website": "jinjianghotels.com",
    "hq_country": "CN",
    "hq_city": "Shanghai",
    "eu_status": "non_eu",
    "industry": "Travel",
    "sub_industry": "Hotels",
    "founded_year": 1991,
    "confidence": "high"
  },
  {
    "name": "Huazhu Group",
    "website": "huazhu.com",
    "hq_country": "CN",
    "hq_city": "Shanghai",
    "eu_status": "non_eu",
    "industry": "Travel",
    "sub_industry": "Hotels",
    "founded_year": 2005,
    "confidence": "high"
  },
  {
    "name": "BTG Homeinns Hotels",
    "website": "homeinns.com",
    "hq_country": "CN",
    "hq_city": "Shanghai",
    "eu_status": "non_eu",
    "industry": "Travel",
    "sub_industry": "Hotels",
    "founded_year": 2002,
    "confidence": "high"
  },
  {
    "name": "Whitbread",
    "website": "whitbread.co.uk",
    "hq_country": "GB",
    "hq_city": "Dunstable",
    "eu_status": "non_eu",
    "industry": "Travel",
    "sub_industry": "Hotels",
    "founded_year": 1742,
    "confidence": "high"
  },
  {
    "name": "Leonardo Hotels",
    "website": "leonardo-hotels.com",
    "hq_country": "IL",
    "hq_city": "Tel Aviv",
    "eu_status": "non_eu",
    "industry": "Travel",
    "sub_industry": "Hotels",
    "founded_year": 1995,
    "confidence": "high"
  },
  {
    "name": "Meininger Hotels",
    "website": "meininger-hotels.com",
    "hq_country": "DE",
    "hq_city": "Berlin",
    "eu_status": "eu",
    "industry": "Travel",
    "sub_industry": "Hotels",
    "founded_year": 1999,
    "confidence": "high"
  },
  {
    "name": "A&O Hostels",
    "website": "aohostels.com",
    "hq_country": "DE",
    "hq_city": "Berlin",
    "eu_status": "eu",
    "industry": "Travel",
    "sub_industry": "Hotels",
    "founded_year": 2000,
    "confidence": "high"
  },
  {
    "name": "Generator Hostels",
    "website": "staygenerator.com",
    "hq_country": "GB",
    "hq_city": "London",
    "eu_status": "non_eu",
    "industry": "Travel",
    "sub_industry": "Hotels",
    "founded_year": 1995,
    "confidence": "high"
  },
  {
    "name": "Freehand Hotels",
    "website": "freehandhotels.com",
    "hq_country": "US",
    "hq_city": "Miami",
    "eu_status": "non_eu",
    "industry": "Travel",
    "sub_industry": "Hotels",
    "founded_year": 2012,
    "confidence": "high"
  },
  {
    "name": "Ace Hotel Group",
    "website": "acehotel.com",
    "hq_country": "US",
    "hq_city": "Portland",
    "eu_status": "non_eu",
    "industry": "Travel",
    "sub_industry": "Hotels",
    "founded_year": 1999,
    "confidence": "high"
  },
  {
    "name": "Soho House",
    "website": "sohohouse.com",
    "hq_country": "GB",
    "hq_city": "London",
    "eu_status": "non_eu",
    "industry": "Travel",
    "sub_industry": "Hotels",
    "founded_year": 1995,
    "confidence": "high"
  },
  {
    "name": "Standard International",
    "website": "standardhotels.com",
    "hq_country": "US",
    "hq_city": "New York",
    "eu_status": "non_eu",
    "industry": "Travel",
    "sub_industry": "Hotels",
    "founded_year": 1999,
    "confidence": "high"
  },
  {
    "name": "Graduate Hotels",
    "website": "graduatehotels.com",
    "hq_country": "US",
    "hq_city": "Chicago",
    "eu_status": "non_eu",
    "industry": "Travel",
    "sub_industry": "Hotels",
    "founded_year": 2014,
    "confidence": "high"
  },
  {
    "name": "Red Roof Inn",
    "website": "redroof.com",
    "hq_country": "US",
    "hq_city": "Columbus",
    "eu_status": "non_eu",
    "industry": "Travel",
    "sub_industry": "Hotels",
    "founded_year": 1973,
    "confidence": "high"
  },
  {
    "name": "La Quinta Inns & Suites",
    "website": "lq.com",
    "hq_country": "US",
    "hq_city": "Dallas",
    "eu_status": "non_eu",
    "industry": "Travel",
    "sub_industry": "Hotels",
    "founded_year": 1968,
    "confidence": "high"
  },
  {
    "name": "Extended Stay America",
    "website": "extendedstayamerica.com",
    "hq_country": "US",
    "hq_city": "Charlotte",
    "eu_status": "non_eu",
    "industry": "Travel",
    "sub_industry": "Hotels",
    "founded_year": 1995,
    "confidence": "high"
  },
  {
    "name": "Highgate Hotels",
    "website": "highgate.com",
    "hq_country": "US",
    "hq_city": "New York",
    "eu_status": "non_eu",
    "industry": "Travel",
    "sub_industry": "Hotels",
    "founded_year": 1988,
    "confidence": "high"
  },
  {
    "name": "Aimbridge Hospitality",
    "website": "aimbridgehospitality.com",
    "hq_country": "US",
    "hq_city": "Dallas",
    "eu_status": "non_eu",
    "industry": "Travel",
    "sub_industry": "Hotels",
    "founded_year": 2003,
    "confidence": "high"
  },
  {
    "name": "SpiceJet",
    "website": "spicejet.com",
    "hq_country": "IN",
    "hq_city": "Gurgaon",
    "eu_status": "non_eu",
    "industry": "Travel",
    "sub_industry": "Airlines",
    "founded_year": 2004,
    "confidence": "high"
  },
  {
    "name": "Air India",
    "website": "airindia.com",
    "hq_country": "IN",
    "hq_city": "New Delhi",
    "eu_status": "non_eu",
    "industry": "Travel",
    "sub_industry": "Airlines",
    "founded_year": 1932,
    "confidence": "high"
  },
  {
    "name": "EgyptAir",
    "website": "egyptair.com",
    "hq_country": "EG",
    "hq_city": "Cairo",
    "eu_status": "non_eu",
    "industry": "Travel",
    "sub_industry": "Airlines",
    "founded_year": 1932,
    "confidence": "high"
  },
  {
    "name": "RIU Hotels & Resorts",
    "website": "riu.com",
    "hq_country": "ES",
    "hq_city": "Palma de Mallorca",
    "eu_status": "eu",
    "industry": "Travel",
    "sub_industry": "Hotels",
    "founded_year": 1953,
    "confidence": "high"
  },
  {
    "name": "Barcel\u00f3 Hotel Group",
    "website": "barcelo.com",
    "hq_country": "ES",
    "hq_city": "Palma de Mallorca",
    "eu_status": "eu",
    "industry": "Travel",
    "sub_industry": "Hotels",
    "founded_year": 1931,
    "confidence": "high"
  },
  {
    "name": "Louvre Hotels Group",
    "website": "louvrehotels.com",
    "hq_country": "FR",
    "hq_city": "Paris",
    "eu_status": "eu",
    "industry": "Travel",
    "sub_industry": "Hotels",
    "founded_year": 1976,
    "confidence": "high"
  },
  {
    "name": "Hard Rock Hotels",
    "website": "hardrockhotels.com",
    "hq_country": "US",
    "hq_city": "Hollywood",
    "eu_status": "non_eu",
    "industry": "Travel",
    "sub_industry": "Hotels",
    "founded_year": 1971,
    "confidence": "high"
  },
  {
    "name": "Explora Journeys",
    "website": "explorajourneys.com",
    "hq_country": "CH",
    "hq_city": "Geneva",
    "eu_status": "non_eu",
    "industry": "Travel",
    "sub_industry": "Cruise Lines",
    "founded_year": 2021,
    "confidence": "high"
  },
  {
    "name": "TAV Airports Holding",
    "website": "tavairports.com",
    "hq_country": "TR",
    "hq_city": "Istanbul",
    "eu_status": "non_eu",
    "industry": "Travel",
    "sub_industry": "Airports",
    "founded_year": 1997,
    "confidence": "high"
  }
]